{"_type":"export","__export_format":4,"__export_date":"2024-06-18T23:33:34.270Z","__export_source":"insomnia.desktop.app:v2023.5.8","resources":[{"_id":"req_c285ba6844324ca9a7ded6baf4c20447","parentId":"fld_9a0510bd5bbb4e378f9fa76c8e05d0ff","modified":1718679934036,"created":1718565715415,"url":"{{ _.base_url }}/users","name":"/users","description":"","method":"GET","body":{},"parameters":[],"headers":[{"name":"User-Agent","value":"insomnia/2023.5.8"}],"authentication":{},"metaSortKey":-1718413505319,"isPrivate":false,"settingStoreCookies":true,"settingSendCookies":true,"settingDisableRenderRequestBody":false,"settingEncodeUrl":true,"settingRebuildPath":true,"settingFollowRedirects":"global","_type":"request"},{"_id":"fld_9a0510bd5bbb4e378f9fa76c8e05d0ff","parentId":"wrk_4b43869bb2e74b4dadb182e9575e1f3d","modified":1718681395257,"created":1718565715413,"name":"Users","description":"","environment":{},"environmentPropertyOrder":null,"metaSortKey":-1718467649684,"_type":"request_group"},{"_id":"wrk_4b43869bb2e74b4dadb182e9575e1f3d","parentId":null,"modified":1718406368730,"created":1718406368730,"name":"Api-proprli","description":"","scope":"collection","_type":"workspace"},{"_id":"req_80f6c9d2bb534c0ab31678a63994ae52","parentId":"fld_63854a4c54c642abbfc8802ee875f416","modified":1718679927744,"created":1718555853778,"url":"{{ _.base_url }}/status","name":"/status","description":"","method":"GET","body":{},"parameters":[],"headers":[{"name":"User-Agent","value":"insomnia/2023.5.8"}],"authentication":{},"metaSortKey":-1718413505319,"isPrivate":false,"settingStoreCookies":true,"settingSendCookies":true,"settingDisableRenderRequestBody":false,"settingEncodeUrl":true,"settingRebuildPath":true,"settingFollowRedirects":"global","_type":"request"},{"_id":"fld_63854a4c54c642abbfc8802ee875f416","parentId":"wrk_4b43869bb2e74b4dadb182e9575e1f3d","modified":1718681399874,"created":1718555853776,"name":"Status","description":"","environment":{},"environmentPropertyOrder":null,"metaSortKey":-1718467649634,"_type":"request_group"},{"_id":"req_690304802aeb448798b2fcdf8e2e843e","parentId":"fld_2835bbb1888a4754887daf26e11c3aeb","modified":1718679919915,"created":1718413490284,"url":"{{ _.base_url }}/buildings","name":"/buildings","description":"","method":"GET","body":{},"parameters":[],"headers":[{"name":"User-Agent","value":"insomnia/2023.5.8"}],"authentication":{},"metaSortKey":-1718413505319,"isPrivate":false,"settingStoreCookies":true,"settingSendCookies":true,"settingDisableRenderRequestBody":false,"settingEncodeUrl":true,"settingRebuildPath":true,"settingFollowRedirects":"global","_type":"request"},{"_id":"fld_2835bbb1888a4754887daf26e11c3aeb","parentId":"wrk_4b43869bb2e74b4dadb182e9575e1f3d","modified":1718555838779,"created":1718413500316,"name":"Buildings","description":"","environment":{},"environmentPropertyOrder":null,"metaSortKey":-1718467649584,"_type":"request_group"},{"_id":"req_c3c168f63bd349cd8b29818d7515244d","parentId":"fld_4551afaed1b04610a151834b76a4df2e","modified":1718681428462,"created":1718414429951,"url":"{{ _.base_url }}/tasks/4","name":"/tasks/{building_id}","description":"","method":"GET","body":{},"parameters":[],"headers":[{"name":"User-Agent","value":"insomnia/2023.5.8"}],"authentication":{},"metaSortKey":-1718467716382,"isPrivate":false,"settingStoreCookies":true,"settingSendCookies":true,"settingDisableRenderRequestBody":false,"settingEncodeUrl":true,"settingRebuildPath":true,"settingFollowRedirects":"global","_type":"request"},{"_id":"fld_4551afaed1b04610a151834b76a4df2e","parentId":"wrk_4b43869bb2e74b4dadb182e9575e1f3d","modified":1718467649484,"created":1718467649484,"name":"Tasks","description":"","environment":{},"environmentPropertyOrder":null,"metaSortKey":-1718467649484,"_type":"request_group"},{"_id":"req_a29742f984854d2f8072cfdd260491ef","parentId":"fld_4551afaed1b04610a151834b76a4df2e","modified":1718681418530,"created":1718467716282,"url":"{{ _.base_url }}/tasks","name":"/tasks","description":"","method":"POST","body":{"mimeType":"application/json","text":"{\n\t\"title\": \"string\",\n\t\"description\": \"string\",\n\t\"creator_id\": 0,\n\t\"assignee_id\": 0,\n\t\"status_id\": 0,\n\t\"building_id\": 0\n}"},"parameters":[],"headers":[{"name":"Content-Type","value":"application/json"},{"name":"User-Agent","value":"insomnia/2023.5.8"}],"authentication":{},"metaSortKey":-1718467716282,"isPrivate":false,"settingStoreCookies":true,"settingSendCookies":true,"settingDisableRenderRequestBody":false,"settingEncodeUrl":true,"settingRebuildPath":true,"settingFollowRedirects":"global","_type":"request"},{"_id":"req_5716642dc801437f9681e4524f907ee1","parentId":"fld_4551afaed1b04610a151834b76a4df2e","modified":1718681371978,"created":1718549113874,"url":"{{ _.base_url }}/tasks/682","name":"/tasks/{id}","description":"","method":"PUT","body":{"mimeType":"application/json","text":"{\n\t\"title\": \"string\",\n\t\"description\": \"string\",\n\t\"status_id\": 0,\n\t\"building_id\": 0,\n\t\"assignee_id\": 0,\n\t\"completed_on\": \"datetime\"\n}"},"parameters":[],"headers":[{"name":"Content-Type","value":"application/json"},{"name":"User-Agent","value":"insomnia/2023.5.8"}],"authentication":{},"metaSortKey":-1718467685276.5,"isPrivate":false,"settingStoreCookies":true,"settingSendCookies":true,"settingDisableRenderRequestBody":false,"settingEncodeUrl":true,"settingRebuildPath":true,"settingFollowRedirects":"global","_type":"request"},{"_id":"req_f462bd7e6b6b4698a3f9c6cd4faf86f3","parentId":"fld_fdea656bcd674ee5a840d742444f1a15","modified":1718679959978,"created":1718552709056,"url":"{{ _.base_url }}/comment","name":"/comment","description":"","method":"POST","body":{"mimeType":"application/json","text":"{\n\t\"comment\": \"string\",\n\t\"task_id\": 0,\n\t\"user_id\": 0\n}"},"parameters":[],"headers":[{"name":"Content-Type","value":"application/json"},{"name":"User-Agent","value":"insomnia/2023.5.8"}],"authentication":{},"metaSortKey":-1718552709056,"isPrivate":false,"settingStoreCookies":true,"settingSendCookies":true,"settingDisableRenderRequestBody":false,"settingEncodeUrl":true,"settingRebuildPath":true,"settingFollowRedirects":"global","_type":"request"},{"_id":"fld_fdea656bcd674ee5a840d742444f1a15","parentId":"wrk_4b43869bb2e74b4dadb182e9575e1f3d","modified":1718557038876,"created":1718552689694,"name":"Comments","description":"","environment":{},"environmentPropertyOrder":null,"metaSortKey":-1718465957322.5,"_type":"request_group"},{"_id":"req_a7912f38c58c4faf9e8e2e980e338b04","parentId":"fld_fdea656bcd674ee5a840d742444f1a15","modified":1718680730922,"created":1718555867939,"url":"{{ _.base_url }}/comment/6","name":"/comment/{id}","description":"","method":"PUT","body":{"mimeType":"application/json","text":"{\n\t\"comment\": \"string\",\n\t\"task_id\": 14\n}"},"parameters":[],"headers":[{"name":"Content-Type","value":"application/json"},{"name":"User-Agent","value":"insomnia/2023.5.8"}],"authentication":{},"metaSortKey":-1718510212669,"isPrivate":false,"settingStoreCookies":true,"settingSendCookies":true,"settingDisableRenderRequestBody":false,"settingEncodeUrl":true,"settingRebuildPath":true,"settingFollowRedirects":"global","_type":"request"},{"_id":"req_c8249887ec90439ebdcb803e8d963b8e","parentId":"fld_4d7189f9fa174978a9451b82317e468b","modified":1718679901473,"created":1718557044309,"url":"{{ _.base_url }}/filters?date_start=2024-06-17","name":"/filters","description":"","method":"GET","body":{},"parameters":[],"headers":[{"name":"User-Agent","value":"insomnia/2023.5.8"}],"authentication":{},"metaSortKey":-1718557044309,"isPrivate":false,"settingStoreCookies":true,"settingSendCookies":true,"settingDisableRenderRequestBody":false,"settingEncodeUrl":true,"settingRebuildPath":true,"settingFollowRedirects":"global","_type":"request"},{"_id":"fld_4d7189f9fa174978a9451b82317e468b","parentId":"wrk_4b43869bb2e74b4dadb182e9575e1f3d","modified":1718557037696,"created":1718557031416,"name":"Filters","description":"","environment":{},"environmentPropertyOrder":null,"metaSortKey":-1718464265161,"_type":"request_group"},{"_id":"env_0c5e25c6224570e8180cfbf4516a0af01e0eeb2f","parentId":"wrk_4b43869bb2e74b4dadb182e9575e1f3d","modified":1718679906981,"created":1718406368736,"name":"Base Environment","data":{"base_url":"http://localhost:8000"},"dataPropertyOrder":{"&":["base_url"]},"color":null,"isPrivate":false,"metaSortKey":1718406368736,"_type":"environment"},{"_id":"jar_0c5e25c6224570e8180cfbf4516a0af01e0eeb2f","parentId":"wrk_4b43869bb2e74b4dadb182e9575e1f3d","modified":1718406368739,"created":1718406368739,"name":"Default Jar","cookies":[],"_type":"cookie_jar"}]}